jsoniq_jupyterlab_extension/__init__.py
jsoniq_jupyterlab_extension/_version.py
jsoniq_jupyterlab_extension/jsoniq_lsp.py
jsoniq_jupyterlab_extension/jsoniq_spec.py
jsoniq_jupyterlab_extension/package.json
jsoniq_jupyterlab_extension/yarn.lock
jsoniq_jupyterlab_extension/node_modules/.yarn-integrity
jsoniq_jupyterlab_extension/node_modules/.bin/antlr4ng
jsoniq_jupyterlab_extension/node_modules/.bin/esbuild
jsoniq_jupyterlab_extension/node_modules/.bin/installServerIntoExtension
jsoniq_jupyterlab_extension/node_modules/.bin/tsx
jsoniq_jupyterlab_extension/node_modules/@esbuild/linux-x64/README.md
jsoniq_jupyterlab_extension/node_modules/@esbuild/linux-x64/package.json
jsoniq_jupyterlab_extension/node_modules/@esbuild/linux-x64/bin/esbuild
jsoniq_jupyterlab_extension/node_modules/antlr4-c3/License.txt
jsoniq_jupyterlab_extension/node_modules/antlr4-c3/package.json
jsoniq_jupyterlab_extension/node_modules/antlr4-c3/readme.md
jsoniq_jupyterlab_extension/node_modules/antlr4-c3/lib/index.cjs
jsoniq_jupyterlab_extension/node_modules/antlr4-c3/lib/index.d.ts
jsoniq_jupyterlab_extension/node_modules/antlr4-c3/lib/index.mjs
jsoniq_jupyterlab_extension/node_modules/antlr4-c3/lib/src/ArrayType.d.ts
jsoniq_jupyterlab_extension/node_modules/antlr4-c3/lib/src/BaseSymbol.d.ts
jsoniq_jupyterlab_extension/node_modules/antlr4-c3/lib/src/BlockSymbol.d.ts
jsoniq_jupyterlab_extension/node_modules/antlr4-c3/lib/src/ClassSymbol.d.ts
jsoniq_jupyterlab_extension/node_modules/antlr4-c3/lib/src/CodeCompletionCore.d.ts
jsoniq_jupyterlab_extension/node_modules/antlr4-c3/lib/src/DuplicateSymbolError.d.ts
jsoniq_jupyterlab_extension/node_modules/antlr4-c3/lib/src/FieldSymbol.d.ts
jsoniq_jupyterlab_extension/node_modules/antlr4-c3/lib/src/FundamentalType.d.ts
jsoniq_jupyterlab_extension/node_modules/antlr4-c3/lib/src/InterfaceSymbol.d.ts
jsoniq_jupyterlab_extension/node_modules/antlr4-c3/lib/src/LiteralSymbol.d.ts
jsoniq_jupyterlab_extension/node_modules/antlr4-c3/lib/src/MethodSymbol.d.ts
jsoniq_jupyterlab_extension-0.1.4.dist-info/METADATA
jsoniq_jupyterlab_extension-0.1.4.dist-info/WHEEL
jsoniq_jupyterlab_extension-0.1.4.dist-info/entry_points.txt
jsoniq_jupyterlab_extension-0.1.4.dist-info/licenses/LICENSE
jsoniq_jupyterlab_extension-0.1.4.dist-info/RECORD
