Metadata-Version: 2.3
Name: jsoniq_jupyterlab_extension
Version: 0.1.4
Dynamic: Keywords
Summary: A JupyterLab extension to enable JSONiq language features within JupyterLab cells.
Project-URL: Homepage, https://github.com/DavidBuzatu-Marian/jsoniq-jupyterlab-extension
Project-URL: Bug Tracker, https://github.com/DavidBuzatu-Marian/jsoniq-jupyterlab-extension/issues
Project-URL: Repository, https://github.com/DavidBuzatu-Marian/jsoniq-jupyterlab-extension.git
Author-email: David-Marian Buzatu <davidm.buzatu@gmail.com>
License: Apache License
License-File: LICENSE
Classifier: Framework :: Jupyter
Classifier: Framework :: Jupyter :: JupyterLab
Classifier: Framework :: Jupyter :: JupyterLab :: 4
Classifier: Framework :: Jupyter :: JupyterLab :: Extensions
Classifier: Framework :: Jupyter :: JupyterLab :: Extensions :: Prebuilt
Classifier: License :: OSI Approved :: Apache Software License
Classifier: Programming Language :: Python
Classifier: Programming Language :: Python :: 3
Classifier: Programming Language :: Python :: 3.8
Classifier: Programming Language :: Python :: 3.9
Classifier: Programming Language :: Python :: 3.10
Classifier: Programming Language :: Python :: 3.11
Classifier: Programming Language :: Python :: 3.12
Requires-Python: >=3.8
